macropython/__init__.py
macropython/classes.py
macropython/keyboard_functions.py
macropython/main.py
macropython/misc_functions.py
macropython/mouse_functions.py
macropython/testing.py
macropython-0.0.1.0.dist-info/LICENSE
macropython-0.0.1.0.dist-info/METADATA
macropython-0.0.1.0.dist-info/WHEEL
macropython-0.0.1.0.dist-info/top_level.txt
macropython-0.0.1.0.dist-info/RECORD
