Metadata-Version: 2.1
Name: macropython
Version: 0.0.1.0
Summary: Make macros easily with macropython
Home-page: https://github.com/Dragon-Batch/macropython
Author: HelloBoi
License: UNKNOWN
Project-URL: Bug Tracker, https://github.com/Dragon-Batch/macropython/issues
Platform: UNKNOWN
Classifier: Programming Language :: Python :: 3
Classifier: License :: OSI Approved :: MIT License
Classifier: Operating System :: OS Independent
Requires-Python: >=3.10
License-File: LICENSE
